uttt_engine/__init__.py
uttt_engine/uttt_engine.py
uttt_engine-0.0.8.dist-info/METADATA
uttt_engine-0.0.8.dist-info/WHEEL
uttt_engine-0.0.8.dist-info/licenses/LICENSE
uttt_engine-0.0.8.dist-info/RECORD
