Metadata-Version: 2.3
Name: uttt_engine
Version: 0.0.8
Summary: A python library for the game of Ultimate Tic-Tac-Toe
Project-URL: Homepage, https://github.com/Minor-Car-Mistake-LLC/UTTT-Engine
Project-URL: Issues, https://github.com/Minor-Car-Mistake-LLC/UTTT-Engine/issues
Author-email: Ike Roy <isaacevansroy@gmail.com>
License-File: LICENSE
Classifier: License :: OSI Approved :: MIT License
Classifier: Operating System :: OS Independent
Classifier: Programming Language :: Python :: 3
Requires-Python: >=3.0
